[
  {
    "value": "abli",
    "label": "Abraham Lincoln Birthplace National Historical Park"
  },
  {"value": "acad", "label": "Acadia National Park"},
  {"value": "adam", "label": "Adams National Historical Park"},
  {"value": "afam", "label": "African American Civil War Memorial"},
  {"value": "afbg", "label": "African Burial Ground National Monument"},
  {"value": "agfo", "label": "Agate Fossil Beds National Monument"},
  {"value": "alka", "label": "Ala Kahakai National Historic Trail"},
  {"value": "alag", "label": "Alagnak Wild River"},
  {"value": "anch", "label": "Alaska Public Lands"},
  {"value": "alca", "label": "Alcatraz Island"},
  {
    "value": "aleu",
    "label": "Aleutian Islands World War II National Historic Area"
  },
  {"value": "alfl", "label": "Alibates Flint Quarries National Monument"},
  {
    "value": "alpo",
    "label": "Allegheny Portage Railroad National Historic Site"
  },
  {"value": "amme", "label": "American Memorial Park"},
  {"value": "amis", "label": "Amistad National Recreation Area"},
  {"value": "anac", "label": "Anacostia Park"},
  {"value": "ande", "label": "Andersonville National Historic Site"},
  {"value": "anjo", "label": "Andrew Johnson National Historic Site"},
  {"value": "ania", "label": "Aniakchak National Monument & Preserve"},
  {"value": "anti", "label": "Antietam National Battlefield"},
  {"value": "apis", "label": "Apostle Islands National Lakeshore"},
  {"value": "appa", "label": "Appalachian National Scenic Trail"},
  {
    "value": "apco",
    "label": "Appomattox Court House National Historical Park"
  },
  {"value": "arch", "label": "Arches National Park"},
  {"value": "arpo", "label": "Arkansas Post National Memorial"},
  {"value": "arho", "label": "Arlington House, The Robert E. Lee Memorial"},
  {"value": "asis", "label": "Assateague Island National Seashore"},
  {"value": "azru", "label": "Aztec Ruins National Monument"},
  {"value": "badl", "label": "Badlands National Park"},
  {"value": "bawa", "label": "Baltimore-Washington Parkway"},
  {"value": "band", "label": "Bandelier National Monument"},
  {
    "value": "bepa",
    "label": "Belmont-Paul Women's Equality National Monument"
  },
  {"value": "beol", "label": "Bent's Old Fort National Historic Site"},
  {"value": "bela", "label": "Bering Land Bridge National Preserve"},
  {"value": "bibe", "label": "Big Bend National Park"},
  {"value": "bicy", "label": "Big Cypress National Preserve"},
  {"value": "biho", "label": "Big Hole National Battlefield"},
  {
    "value": "biso",
    "label": "Big South Fork National River & Recreation Area"
  },
  {"value": "bith", "label": "Big Thicket National Preserve"},
  {"value": "bica", "label": "Bighorn Canyon National Recreation Area"},
  {"value": "bicr", "label": "Birmingham Civil Rights National Monument"},
  {"value": "bisc", "label": "Biscayne National Park"},
  {"value": "blca", "label": "Black Canyon Of The Gunnison National Park"},
  {
    "value": "blrv",
    "label": "Blackstone River Valley National Historical Park"
  },
  {"value": "blri", "label": "Blue Ridge Parkway"},
  {"value": "blue", "label": "Bluestone National Scenic River"},
  {"value": "bowa", "label": "Booker T Washington National Monument"},
  {
    "value": "boaf",
    "label": "Boston African American National Historic Site"
  },
  {
    "value": "boha",
    "label": "Boston Harbor Islands National Recreation Area"
  },
  {"value": "bost", "label": "Boston National Historical Park"},
  {"value": "brcr", "label": "Brices Cross Roads National Battlefield Site"},
  {
    "value": "brvb",
    "label": "Brown v. Board of Education National Historic Site"
  },
  {"value": "brca", "label": "Bryce Canyon National Park"},
  {"value": "buis", "label": "Buck Island Reef National Monument"},
  {"value": "buff", "label": "Buffalo National River"},
  {"value": "cabr", "label": "Cabrillo National Monument"},
  {"value": "cali", "label": "California National Historic Trail"},
  {"value": "cane", "label": "Camp Nelson National Monument"},
  {"value": "cana", "label": "Canaveral National Seashore"},
  {"value": "cari", "label": "Cane River Creole National Historical Park"},
  {"value": "cach", "label": "Canyon de Chelly National Monument"},
  {"value": "cany", "label": "Canyonlands National Park"},
  {"value": "caco", "label": "Cape Cod National Seashore"},
  {"value": "caha", "label": "Cape Hatteras National Seashore"},
  {
    "value": "came",
    "label": "Cape Henry Memorial Part of Colonial National Historical Park"
  },
  {"value": "cakr", "label": "Cape Krusenstern National Monument"},
  {"value": "calo", "label": "Cape Lookout National Seashore"},
  {"value": "cahi", "label": "Capitol Hill Parks"},
  {"value": "care", "label": "Capitol Reef National Park"},
  {
    "value": "cajo",
    "label": "Captain John Smith Chesapeake National Historic Trail"
  },
  {"value": "cavo", "label": "Capulin Volcano National Monument"},
  {"value": "carl", "label": "Carl Sandburg Home National Historic Site"},
  {"value": "cave", "label": "Carlsbad Caverns National Park"},
  {"value": "cawo", "label": "Carter G. Woodson Home National Historic Site"},
  {"value": "cagr", "label": "Casa Grande Ruins National Monument"},
  {"value": "casa", "label": "Castillo de San Marcos National Monument"},
  {"value": "cacl", "label": "Castle Clinton National Monument"},
  {"value": "camo", "label": "Castle Mountains National Monument"},
  {"value": "cato", "label": "Catoctin Mountain Park"},
  {"value": "cebr", "label": "Cedar Breaks National Monument"},
  {
    "value": "cebe",
    "label": "Cedar Creek & Belle Grove National Historical Park"
  },
  {"value": "chcu", "label": "Chaco Culture National Historical Park"},
  {"value": "cham", "label": "Chamizal National Memorial"},
  {"value": "chis", "label": "Channel Islands National Park"},
  {"value": "chpi", "label": "Charles Pinckney National Historic Site"},
  {
    "value": "chyo",
    "label": "Charles Young Buffalo Soldiers National Monument"
  },
  {"value": "chat", "label": "Chattahoochee River National Recreation Area"},
  {
    "value": "choh",
    "label": "Chesapeake & Ohio Canal National Historical Park"
  },
  {"value": "cbpo", "label": "Chesapeake Bay"},
  {
    "value": "chch",
    "label": "Chickamauga & Chattanooga National Military Park"
  },
  {"value": "chic", "label": "Chickasaw National Recreation Area"},
  {"value": "chir", "label": "Chiricahua National Monument"},
  {"value": "chri", "label": "Christiansted National Historic Site"},
  {"value": "ciro", "label": "City Of Rocks National Reserve"},
  {"value": "cwdw", "label": "Civil War Defenses of Washington"},
  {"value": "clba", "label": "Clara Barton National Historic Site"},
  {"value": "colo", "label": "Colonial National Historical Park"},
  {"value": "colm", "label": "Colorado National Monument"},
  {"value": "colt", "label": "Coltsville National Historical Park"},
  {"value": "cong", "label": "Congaree National Park"},
  {"value": "coga", "label": "Constitution Gardens"},
  {"value": "coro", "label": "Coronado National Memorial"},
  {"value": "cowp", "label": "Cowpens National Battlefield"},
  {"value": "crla", "label": "Crater Lake National Park"},
  {
    "value": "crmo",
    "label": "Craters Of The Moon National Monument & Preserve"
  },
  {"value": "cuga", "label": "Cumberland Gap National Historical Park"},
  {"value": "cuis", "label": "Cumberland Island National Seashore"},
  {"value": "cure", "label": "Curecanti National Recreation Area"},
  {"value": "cuva", "label": "Cuyahoga Valley National Park"},
  {"value": "cech", "label": "César E. Chávez National Monument"},
  {
    "value": "daav",
    "label": "Dayton Aviation Heritage National Historical Park"
  },
  {"value": "deso", "label": "De Soto National Memorial"},
  {"value": "deva", "label": "Death Valley National Park"},
  {"value": "dewa", "label": "Delaware Water Gap National Recreation Area"},
  {"value": "dena", "label": "Denali National Park & Preserve"},
  {"value": "depo", "label": "Devils Postpile National Monument"},
  {"value": "deto", "label": "Devils Tower National Monument"},
  {"value": "dino", "label": "Dinosaur National Monument"},
  {"value": "drto", "label": "Dry Tortugas National Park"},
  {"value": "ddem", "label": "Dwight D. Eisenhower Memorial"},
  {"value": "ebla", "label": "Ebey's Landing National Historical Reserve"},
  {"value": "edal", "label": "Edgar Allan Poe National Historic Site"},
  {"value": "efmo", "label": "Effigy Mounds National Monument"},
  {"value": "eise", "label": "Eisenhower National Historic Site"},
  {
    "value": "elca",
    "label": "El Camino Real de Tierra Adentro National Historic Trail"
  },
  {
    "value": "elte",
    "label": "El Camino Real de los Tejas National Historic Trail"
  },
  {"value": "elma", "label": "El Malpais National Monument"},
  {"value": "elmo", "label": "El Morro National Monument"},
  {"value": "elro", "label": "Eleanor Roosevelt National Historic Site"},
  {
    "value": "elis",
    "label": "Ellis Island Part of Statue of Liberty National Monument"
  },
  {"value": "euon", "label": "Eugene O'Neill National Historic Site"},
  {"value": "ever", "label": "Everglades National Park"},
  {"value": "feha", "label": "Federal Hall National Memorial"},
  {"value": "fiis", "label": "Fire Island National Seashore"},
  {"value": "fila", "label": "First Ladies National Historic Site"},
  {"value": "frst", "label": "First State National Historical Park"},
  {"value": "flni", "label": "Flight 93 National Memorial"},
  {"value": "flfo", "label": "Florissant Fossil Beds National Monument"},
  {"value": "foth", "label": "Ford's Theatre"},
  {"value": "fobo", "label": "Fort Bowie National Historic Site"},
  {"value": "foda", "label": "Fort Davis National Historic Site"},
  {"value": "fodo", "label": "Fort Donelson National Battlefield"},
  {"value": "fodu", "label": "Fort Dupont Park"},
  {"value": "fofo", "label": "Fort Foote Park"},
  {"value": "fofr", "label": "Fort Frederica National Monument"},
  {"value": "fola", "label": "Fort Laramie National Historic Site"},
  {"value": "fols", "label": "Fort Larned National Historic Site"},
  {"value": "foma", "label": "Fort Matanzas National Monument"},
  {
    "value": "fomc",
    "label": "Fort McHenry National Monument and Historic Shrine"
  },
  {"value": "fomr", "label": "Fort Monroe National Monument"},
  {"value": "fone", "label": "Fort Necessity National Battlefield"},
  {"value": "fopo", "label": "Fort Point National Historic Site"},
  {"value": "fopu", "label": "Fort Pulaski National Monument"},
  {"value": "fora", "label": "Fort Raleigh National Historic Site"},
  {"value": "fosc", "label": "Fort Scott National Historic Site"},
  {"value": "fosm", "label": "Fort Smith National Historic Site"},
  {"value": "fost", "label": "Fort Stanwix National Monument"},
  {
    "value": "fosu",
    "label": "Fort Sumter and Fort Moultrie National Historical Park"
  },
  {"value": "foun", "label": "Fort Union National Monument"},
  {
    "value": "fous",
    "label": "Fort Union Trading Post National Historic Site"
  },
  {"value": "fova", "label": "Fort Vancouver National Historic Site"},
  {"value": "fowa", "label": "Fort Washington Park"},
  {"value": "fobu", "label": "Fossil Butte National Monument"},
  {"value": "frde", "label": "Franklin Delano Roosevelt Memorial"},
  {"value": "frdo", "label": "Frederick Douglass National Historic Site"},
  {"value": "frla", "label": "Frederick Law Olmsted National Historic Site"},
  {
    "value": "frsp",
    "label": "Fredericksburg & Spotsylvania National Military Park"
  },
  {"value": "frri", "label": "Freedom Riders National Monument"},
  {"value": "frhi", "label": "Friendship Hill National Historic Site"},
  {"value": "gaar", "label": "Gates Of The Arctic National Park & Preserve"},
  {"value": "jeff", "label": "Gateway Arch National Park"},
  {"value": "gate", "label": "Gateway National Recreation Area"},
  {"value": "gari", "label": "Gauley River National Recreation Area"},
  {"value": "gegr", "label": "General Grant National Memorial"},
  {"value": "gero", "label": "George Rogers Clark National Historical Park"},
  {
    "value": "gewa",
    "label": "George Washington Birthplace National Monument"
  },
  {"value": "gwca", "label": "George Washington Carver National Monument"},
  {"value": "gwmp", "label": "George Washington Memorial Parkway"},
  {"value": "gett", "label": "Gettysburg National Military Park"},
  {"value": "gicl", "label": "Gila Cliff Dwellings National Monument"},
  {"value": "glba", "label": "Glacier Bay National Park & Preserve"},
  {"value": "glac", "label": "Glacier National Park"},
  {"value": "glca", "label": "Glen Canyon National Recreation Area"},
  {"value": "glec", "label": "Glen Echo Park"},
  {"value": "glde", "label": "Gloria Dei Church National Historic Site"},
  {"value": "goga", "label": "Golden Gate National Recreation Area"},
  {"value": "gosp", "label": "Golden Spike National Historical Park"},
  {"value": "gois", "label": "Governors Island National Monument"},
  {"value": "grca", "label": "Grand Canyon National Park"},
  {"value": "para", "label": "Grand Canyon-Parashant National Monument"},
  {"value": "grpo", "label": "Grand Portage National Monument"},
  {"value": "grte", "label": "Grand Teton National Park"},
  {"value": "grko", "label": "Grant-Kohrs Ranch National Historic Site"},
  {"value": "grba", "label": "Great Basin National Park"},
  {"value": "greg", "label": "Great Egg Harbor River"},
  {"value": "grfa", "label": "Great Falls Park"},
  {"value": "grsa", "label": "Great Sand Dunes National Park & Preserve"},
  {"value": "grsm", "label": "Great Smoky Mountains National Park"},
  {"value": "grsp", "label": "Green Springs"},
  {"value": "gree", "label": "Greenbelt Park"},
  {"value": "gumo", "label": "Guadalupe Mountains National Park"},
  {"value": "guco", "label": "Guilford Courthouse National Military Park"},
  {"value": "guis", "label": "Gulf Islands National Seashore"},
  {"value": "hafo", "label": "Hagerman Fossil Beds National Monument"},
  {"value": "hale", "label": "Haleakalā National Park"},
  {"value": "hagr", "label": "Hamilton Grange National Memorial"},
  {"value": "hamp", "label": "Hampton National Historic Site"},
  {"value": "haha", "label": "Harmony Hall"},
  {"value": "hafe", "label": "Harpers Ferry National Historical Park"},
  {"value": "hart", "label": "Harriet Tubman National Historical Park"},
  {
    "value": "hatu",
    "label": "Harriet Tubman Underground Railroad National Historical Park"
  },
  {"value": "hstr", "label": "Harry S Truman National Historic Site"},
  {"value": "havo", "label": "Hawaiʻi Volcanoes National Park"},
  {"value": "heho", "label": "Herbert Hoover National Historic Site"},
  {
    "value": "jame",
    "label": "Historic Jamestowne Part of Colonial National Historical Park"
  },
  {
    "value": "hofr",
    "label": "Home Of Franklin D Roosevelt National Historic Site"
  },
  {"value": "home", "label": "Homestead National Historical Park"},
  {"value": "hono", "label": "Honouliuli National Historic Site"},
  {"value": "hocu", "label": "Hopewell Culture National Historical Park"},
  {"value": "hofu", "label": "Hopewell Furnace National Historic Site"},
  {"value": "hobe", "label": "Horseshoe Bend National Military Park"},
  {"value": "hosp", "label": "Hot Springs National Park"},
  {"value": "hove", "label": "Hovenweep National Monument"},
  {"value": "hutr", "label": "Hubbell Trading Post National Historic Site"},
  {"value": "iafl", "label": "Ice Age Floods National Geologic Trail"},
  {"value": "iatr", "label": "Ice Age National Scenic Trail"},
  {"value": "inde", "label": "Independence National Historical Park"},
  {"value": "indu", "label": "Indiana Dunes National Park"},
  {"value": "isro", "label": "Isle Royale National Park"},
  {"value": "inup", "label": "Iñupiat Heritage Center"},
  {"value": "jaga", "label": "James A Garfield National Historic Site"},
  {
    "value": "jela",
    "label": "Jean Lafitte National Historical Park and Preserve"
  },
  {"value": "jeca", "label": "Jewel Cave National Monument"},
  {"value": "jica", "label": "Jimmy Carter National Historical Park"},
  {"value": "joda", "label": "John Day Fossil Beds National Monument"},
  {
    "value": "jofi",
    "label": "John Fitzgerald Kennedy National Historic Site"
  },
  {"value": "jomu", "label": "John Muir National Historic Site"},
  {"value": "jofl", "label": "Johnstown Flood National Memorial"},
  {"value": "jotr", "label": "Joshua Tree National Park"},
  {"value": "juba", "label": "Juan Bautista de Anza National Historic Trail"},
  {"value": "kala", "label": "Kalaupapa National Historical Park"},
  {"value": "kaho", "label": "Kaloko-Honokōhau National Historical Park"},
  {"value": "kaww", "label": "Katahdin Woods and Waters National Monument"},
  {"value": "katm", "label": "Katmai National Park & Preserve"},
  {"value": "kefj", "label": "Kenai Fjords National Park"},
  {"value": "keaq", "label": "Kenilworth Park & Aquatic Gardens"},
  {"value": "kemo", "label": "Kennesaw Mountain National Battlefield Park"},
  {"value": "kewe", "label": "Keweenaw National Historical Park"},
  {"value": "kimo", "label": "Kings Mountain National Military Park"},
  {
    "value": "klse",
    "label": "Klondike Gold Rush - Seattle Unit National Historical Park"
  },
  {"value": "klgo", "label": "Klondike Gold Rush National Historical Park"},
  {
    "value": "knri",
    "label": "Knife River Indian Villages National Historic Site"
  },
  {"value": "kova", "label": "Kobuk Valley National Park"},
  {"value": "kowa", "label": "Korean War Veterans Memorial"},
  {"value": "lyba", "label": "LBJ Memorial Grove on the Potomac"},
  {"value": "lacl", "label": "Lake Clark National Park & Preserve"},
  {"value": "lake", "label": "Lake Mead National Recreation Area"},
  {"value": "lamr", "label": "Lake Meredith National Recreation Area"},
  {"value": "laro", "label": "Lake Roosevelt National Recreation Area"},
  {"value": "lavo", "label": "Lassen Volcanic National Park"},
  {"value": "labe", "label": "Lava Beds National Monument"},
  {"value": "lecl", "label": "Lewis & Clark National Historic Trail"},
  {"value": "lewi", "label": "Lewis and Clark National Historical Park"},
  {"value": "libo", "label": "Lincoln Boyhood National Memorial"},
  {"value": "liho", "label": "Lincoln Home National Historic Site"},
  {"value": "linc", "label": "Lincoln Memorial"},
  {"value": "libi", "label": "Little Bighorn Battlefield National Monument"},
  {"value": "liri", "label": "Little River Canyon National Preserve"},
  {
    "value": "chsc",
    "label": "Little Rock Central High School National Historic Site"
  },
  {
    "value": "long",
    "label": "Longfellow House Washington's Headquarters National Historic Site"
  },
  {"value": "lowe", "label": "Lowell National Historical Park"},
  {"value": "lode", "label": "Lower Delaware National Wild and Scenic River"},
  {
    "value": "loea",
    "label": "Lower East Side Tenement Museum National Historic Site"
  },
  {"value": "lyjo", "label": "Lyndon B Johnson National Historical Park"},
  {"value": "mawa", "label": "Maggie L Walker National Historic Site"},
  {"value": "maac", "label": "Maine Acadian Culture"},
  {"value": "maca", "label": "Mammoth Cave National Park"},
  {"value": "mana", "label": "Manassas National Battlefield Park"},
  {"value": "mapr", "label": "Manhattan Project National Historical Park"},
  {"value": "manz", "label": "Manzanar National Historic Site"},
  {
    "value": "mabi",
    "label": "Marsh - Billings - Rockefeller National Historical Park"
  },
  {"value": "mlkm", "label": "Martin Luther King, Jr. Memorial"},
  {
    "value": "malu",
    "label": "Martin Luther King, Jr. National Historical Park"
  },
  {"value": "mava", "label": "Martin Van Buren National Historic Site"},
  {
    "value": "mamc",
    "label": "Mary McLeod Bethune Council House National Historic Site"
  },
  {
    "value": "memy",
    "label": "Medgar and Myrlie Evers Home National Monument"
  },
  {"value": "meve", "label": "Mesa Verde National Park"},
  {"value": "misp", "label": "Mill Springs Battlefield National Monument"},
  {"value": "miin", "label": "Minidoka National Historic Site"},
  {"value": "mima", "label": "Minute Man National Historical Park"},
  {"value": "mimi", "label": "Minuteman Missile National Historic Site"},
  {
    "value": "miss",
    "label": "Mississippi National River and Recreation Area"
  },
  {"value": "mnrr", "label": "Missouri National Recreational River"},
  {"value": "moja", "label": "Mojave National Preserve"},
  {"value": "mono", "label": "Monocacy National Battlefield"},
  {"value": "moca", "label": "Montezuma Castle National Monument"},
  {"value": "mocr", "label": "Moores Creek National Battlefield"},
  {"value": "mopi", "label": "Mormon Pioneer National Historic Trail"},
  {"value": "morr", "label": "Morristown National Historical Park"},
  {"value": "mora", "label": "Mount Rainier National Park"},
  {"value": "moru", "label": "Mount Rushmore National Memorial"},
  {"value": "muwo", "label": "Muir Woods National Monument"},
  {"value": "natc", "label": "Natchez National Historical Park"},
  {"value": "natt", "label": "Natchez Trace National Scenic Trail"},
  {"value": "natr", "label": "Natchez Trace Parkway"},
  {"value": "nace", "label": "National Capital Parks-East"},
  {"value": "nama", "label": "National Mall and Memorial Parks"},
  {"value": "npsa", "label": "National Park of American Samoa"},
  {"value": "npnh", "label": "National Parks of New York Harbor"},
  {"value": "nabr", "label": "Natural Bridges National Monument"},
  {"value": "nava", "label": "Navajo National Monument"},
  {"value": "nebe", "label": "New Bedford Whaling National Historical Park"},
  {"value": "neen", "label": "New England National Scenic Trail"},
  {"value": "pine", "label": "New Jersey Pinelands National Reserve"},
  {"value": "jazz", "label": "New Orleans Jazz National Historical Park"},
  {"value": "neri", "label": "New River Gorge National Park and Preserve"},
  {"value": "nepe", "label": "Nez Perce National Historical Park"},
  {"value": "nico", "label": "Nicodemus National Historic Site"},
  {"value": "nisi", "label": "Ninety Six National Historic Site"},
  {"value": "niob", "label": "Niobrara National Scenic River"},
  {"value": "noat", "label": "Noatak National Preserve"},
  {"value": "noca", "label": "North Cascades National Park"},
  {"value": "noco", "label": "North Country National Scenic Trail"},
  {"value": "obed", "label": "Obed Wild & Scenic River"},
  {"value": "ocmu", "label": "Ocmulgee Mounds National Historical Park"},
  {"value": "okci", "label": "Oklahoma City National Memorial"},
  {"value": "olsp", "label": "Old Spanish National Historic Trail"},
  {"value": "olym", "label": "Olympic National Park"},
  {"value": "orca", "label": "Oregon Caves National Monument & Preserve"},
  {"value": "oreg", "label": "Oregon National Historic Trail"},
  {"value": "orpi", "label": "Organ Pipe Cactus National Monument"},
  {"value": "ovvi", "label": "Overmountain Victory National Historic Trail"},
  {"value": "oxhi", "label": "Oxon Cove Park & Oxon Hill Farm"},
  {"value": "ozar", "label": "Ozark National Scenic Riverways"},
  {"value": "pais", "label": "Padre Island National Seashore"},
  {
    "value": "paal",
    "label": "Palo Alto Battlefield National Historical Park"
  },
  {"value": "pagr", "label": "Paterson Great Falls National Historical Park"},
  {"value": "peri", "label": "Pea Ridge National Military Park"},
  {"value": "valr", "label": "Pearl Harbor National Memorial"},
  {"value": "peco", "label": "Pecos National Historical Park"},
  {"value": "paav", "label": "Pennsylvania Avenue"},
  {
    "value": "pevi",
    "label": "Perry's Victory & International Peace Memorial"
  },
  {"value": "pete", "label": "Petersburg National Battlefield"},
  {"value": "pefo", "label": "Petrified Forest National Park"},
  {"value": "petr", "label": "Petroglyph National Monument"},
  {"value": "piro", "label": "Pictured Rocks National Lakeshore"},
  {"value": "pinn", "label": "Pinnacles National Park"},
  {"value": "pisp", "label": "Pipe Spring National Monument"},
  {"value": "pipe", "label": "Pipestone National Monument"},
  {"value": "pisc", "label": "Piscataway Park"},
  {"value": "pore", "label": "Point Reyes National Seashore"},
  {"value": "poex", "label": "Pony Express National Historic Trail"},
  {"value": "poch", "label": "Port Chicago Naval Magazine National Memorial"},
  {"value": "pohe", "label": "Potomac Heritage National Scenic Trail"},
  {"value": "popo", "label": "Poverty Point National Monument"},
  {
    "value": "wicl",
    "label": "President William Jefferson Clinton Birthplace Home National Historic Site"
  },
  {"value": "whho", "label": "President's Park (White House)"},
  {"value": "prsf", "label": "Presidio of San Francisco"},
  {"value": "prwi", "label": "Prince William Forest Park"},
  {"value": "pull", "label": "Pullman National Monument"},
  {"value": "puho", "label": "Puʻuhonua o Hōnaunau National Historical Park"},
  {"value": "puhe", "label": "Puʻukoholā Heiau National Historic Site"},
  {"value": "rabr", "label": "Rainbow Bridge National Monument"},
  {"value": "reer", "label": "Reconstruction Era National Historical Park"},
  {"value": "redw", "label": "Redwood National and State Parks"},
  {"value": "rich", "label": "Richmond National Battlefield Park"},
  {"value": "rigr", "label": "Rio Grande Wild & Scenic River"},
  {"value": "rira", "label": "River Raisin National Battlefield Park"},
  {"value": "rocr", "label": "Rock Creek Park"},
  {"value": "romo", "label": "Rocky Mountain National Park"},
  {"value": "rowi", "label": "Roger Williams National Memorial"},
  {"value": "roca", "label": "Roosevelt Campobello International Park"},
  {
    "value": "rori",
    "label": "Rosie the Riveter WWII Home Front National Historical Park"
  },
  {"value": "ruca", "label": "Russell Cave National Monument"},
  {"value": "sahi", "label": "Sagamore Hill National Historic Site"},
  {"value": "sagu", "label": "Saguaro National Park"},
  {
    "value": "sacr",
    "label": "Saint Croix Island International Historic Site"
  },
  {"value": "sacn", "label": "Saint Croix National Scenic Riverway"},
  {"value": "sapa", "label": "Saint Paul's Church National Historic Site"},
  {"value": "saga", "label": "Saint-Gaudens National Historical Park"},
  {"value": "sama", "label": "Salem Maritime National Historic Site"},
  {"value": "sapu", "label": "Salinas Pueblo Missions National Monument"},
  {
    "value": "sari",
    "label": "Salt River Bay National Historical Park and Ecological Preserve"
  },
  {"value": "saan", "label": "San Antonio Missions National Historical Park"},
  {
    "value": "safr",
    "label": "San Francisco Maritime National Historical Park"
  },
  {"value": "sajh", "label": "San Juan Island National Historical Park"},
  {"value": "saju", "label": "San Juan National Historic Site"},
  {"value": "sand", "label": "Sand Creek Massacre National Historic Site"},
  {"value": "safe", "label": "Santa Fe National Historic Trail"},
  {
    "value": "samo",
    "label": "Santa Monica Mountains National Recreation Area"
  },
  {"value": "sara", "label": "Saratoga National Historical Park"},
  {"value": "sair", "label": "Saugus Iron Works National Historic Site"},
  {"value": "scbl", "label": "Scotts Bluff National Monument"},
  {"value": "semo", "label": "Selma To Montgomery National Historic Trail"},
  {"value": "seki", "label": "Sequoia & Kings Canyon National Parks"},
  {"value": "shen", "label": "Shenandoah National Park"},
  {"value": "shil", "label": "Shiloh National Military Park"},
  {"value": "sitk", "label": "Sitka National Historical Park"},
  {"value": "slbe", "label": "Sleeping Bear Dunes National Lakeshore"},
  {"value": "spar", "label": "Springfield Armory National Historic Site"},
  {"value": "stsp", "label": "Star-Spangled Banner National Historic Trail"},
  {"value": "stli", "label": "Statue Of Liberty National Monument"},
  {"value": "stge", "label": "Ste. Geneviève National Historical Park"},
  {"value": "stea", "label": "Steamtown National Historic Site"},
  {"value": "stri", "label": "Stones River National Battlefield"},
  {"value": "sucr", "label": "Sunset Crater Volcano National Monument"},
  {"value": "tapr", "label": "Tallgrass Prairie National Preserve"},
  {"value": "thko", "label": "Thaddeus Kosciuszko National Memorial"},
  {
    "value": "thrb",
    "label": "Theodore Roosevelt Birthplace National Historic Site"
  },
  {
    "value": "thri",
    "label": "Theodore Roosevelt Inaugural National Historic Site"
  },
  {"value": "this", "label": "Theodore Roosevelt Island"},
  {"value": "thro", "label": "Theodore Roosevelt National Park"},
  {"value": "thco", "label": "Thomas Cole National Historic Site"},
  {"value": "edis", "label": "Thomas Edison National Historical Park"},
  {"value": "thje", "label": "Thomas Jefferson Memorial"},
  {"value": "thst", "label": "Thomas Stone National Historic Site"},
  {"value": "tica", "label": "Timpanogos Cave National Monument"},
  {"value": "timu", "label": "Timucuan Ecological & Historic Preserve"},
  {"value": "tont", "label": "Tonto National Monument"},
  {"value": "tosy", "label": "Touro Synagogue National Historic Site"},
  {"value": "trte", "label": "Trail Of Tears National Historic Trail"},
  {"value": "tule", "label": "Tule Lake National Monument"},
  {"value": "tusk", "label": "Tule Springs Fossil Beds National Monument"},
  {"value": "tuma", "label": "Tumacácori National Historical Park"},
  {"value": "tupe", "label": "Tupelo National Battlefield"},
  {"value": "tuai", "label": "Tuskegee Airmen National Historic Site"},
  {"value": "tuin", "label": "Tuskegee Institute National Historic Site"},
  {"value": "tuzi", "label": "Tuzigoot National Monument"},
  {"value": "ulsg", "label": "Ulysses S Grant National Historic Site"},
  {"value": "upde", "label": "Upper Delaware Scenic & Recreational River"},
  {"value": "vall", "label": "Valles Caldera National Preserve"},
  {"value": "vafo", "label": "Valley Forge National Historical Park"},
  {"value": "vama", "label": "Vanderbilt Mansion National Historic Site"},
  {"value": "vick", "label": "Vicksburg National Military Park"},
  {"value": "vive", "label": "Vietnam Veterans Memorial"},
  {"value": "vicr", "label": "Virgin Islands Coral Reef National Monument"},
  {"value": "viis", "label": "Virgin Islands National Park"},
  {"value": "voya", "label": "Voyageurs National Park"},
  {"value": "waco", "label": "Waco Mammoth National Monument"},
  {"value": "waca", "label": "Walnut Canyon National Monument"},
  {"value": "wapa", "label": "War In The Pacific National Historical Park"},
  {"value": "wamo", "label": "Washington Monument"},
  {
    "value": "waro",
    "label": "Washington-Rochambeau Revolutionary Route National Historic Trail"
  },
  {"value": "waba", "label": "Washita Battlefield National Historic Site"},
  {"value": "wefa", "label": "Weir Farm National Historical Park"},
  {"value": "whis", "label": "Whiskeytown National Recreation Area"},
  {"value": "whsa", "label": "White Sands National Park"},
  {"value": "whmi", "label": "Whitman Mission National Historic Site"},
  {"value": "wiho", "label": "William Howard Taft National Historic Site"},
  {"value": "wicr", "label": "Wilson's Creek National Battlefield"},
  {"value": "wica", "label": "Wind Cave National Park"},
  {"value": "wing", "label": "Wing Luke Museum Affiliated Area"},
  {
    "value": "wotr",
    "label": "Wolf Trap National Park for the Performing Arts"
  },
  {"value": "wori", "label": "Women's Rights National Historical Park"},
  {"value": "wwim", "label": "World War I Memorial"},
  {"value": "wwii", "label": "World War II Memorial"},
  {"value": "wrst", "label": "Wrangell - St Elias National Park & Preserve"},
  {"value": "wrbr", "label": "Wright Brothers National Memorial"},
  {"value": "wupa", "label": "Wupatki National Monument"},
  {"value": "yell", "label": "Yellowstone National Park"},
  {
    "value": "york",
    "label": "Yorktown Battlefield Part of Colonial National Historical Park"
  },
  {"value": "yose", "label": "Yosemite National Park"},
  {"value": "yuho", "label": "Yucca House National Monument"},
  {"value": "yuch", "label": "Yukon - Charley Rivers National Preserve"},
  {"value": "zion", "label": "Zion National Park"}
]
